csm/fast.cpython-39-x86_64-linux-gnu.so
csm/version.py
csm/__init__.py
csm/input_output/arguments.py
csm/input_output/formatters.py
csm/input_output/__init__.py
csm/input_output/readers.py
csm/input_output/writers.py
csm/molecule/atom.py
csm/molecule/__init__.py
csm/molecule/normalizations.py
csm/molecule/molecule.py
csm/main/normcsm.py
csm/main/openbabel_fix.py
csm/main/__init__.py
csm/main/csm_run.py
csm/CPP_wrapper/fast.cpp
csm/calculations/basic_calculations.py
csm/calculations/permuters.py
csm/calculations/trivial_calculations.py
csm/calculations/exact_calculations.py
csm/calculations/__init__.py
csm/calculations/data_classes.py
csm/calculations/constants.py
csm/calculations/approx/dirs.py
csm/calculations/approx/statistics.py
csm/calculations/approx/perm_builders.py
csm/calculations/approx/approximators.py
csm/calculations/approx/__init__.py
csm-1.3.2b1.dist-info/entry_points.txt
csm-1.3.2b1.dist-info/METADATA
csm-1.3.2b1.dist-info/top_level.txt
csm-1.3.2b1.dist-info/WHEEL
csm-1.3.2b1.dist-info/RECORD
