Metadata-Version: 2.1
Name: csm
Version: 1.3.2b1
Summary: The Continuous Symmetry Measure
Home-page: http://www.csm.huji.ac.il/new/
Author: The Research Software Company
Author-email: itay@chelem.co.il
License: Chelem
Platform: UNKNOWN
Classifier: Development Status :: 4 - Beta
Classifier: Environment :: Console
Classifier: Intended Audience :: Science/Research
Classifier: License :: OSI Approved :: GNU General Public License v2 or later (GPLv2+)
Classifier: Operating System :: OS Independent
Classifier: Programming Language :: Python
Classifier: Programming Language :: Python :: 3.7
Classifier: Programming Language :: Python :: 3.8
Classifier: Programming Language :: Python :: 3.9
Classifier: Programming Language :: Python :: 3.10
Classifier: Topic :: Scientific/Engineering :: Chemistry
